mailupy/__init__.py
mailupy/client.py
mailupy/exceptions.py
mailupy/utils.py
tests/__init__.py
tests/test_main.py
tests/tools.py
mailupy-1.1.4.dist-info/LICENSE
mailupy-1.1.4.dist-info/METADATA
mailupy-1.1.4.dist-info/WHEEL
mailupy-1.1.4.dist-info/top_level.txt
mailupy-1.1.4.dist-info/RECORD
