Metadata-Version: 2.1
Name: mailupy
Version: 1.1.4
Summary: Yet another Mailup Python client
Author-email: Lotrèk <dimmitutto@lotrek.it>
License: MIT
Project-URL: Homepage, https://github.com/lotrekagency/mailupy
Keywords: mailup,python,api,client
Classifier: Environment :: Web Environment
Classifier: Intended Audience :: Developers
Classifier: Programming Language :: Python
Classifier: Programming Language :: Python :: 3
Requires-Python: >=3.6
License-File: LICENSE
Requires-Dist: requests ==2.31.0
